{"SPY": {"c": 664.73, "d": -6.56, "dp": -0.9772, "h": 672.26, "l": 664.55, "o": 672.26, "pc": 671.29, "t": 1761150704}, "SMH": {"c": 335.82, "d": -9.48, "dp": -2.7454, "h": 344.86, "l": 335.35, "o": 343.87, "pc": 345.3, "t": 1761150703}, "ABAT": {"c": 5.5401, "d": -0.5599, "dp": -9.1787, "h": 6.39, "l": 5.51, "o": 5.68, "pc": 6.1, "t": 1761150699}, "UUUU": {"c": 20.5, "d": -0.13, "dp": -0.6302, "h": 21.37, "l": 18.76, "o": 18.89, "pc": 20.63, "t": 1761150704}, "ALAB": {"c": 150.1902, "d": -7.3198, "dp": -4.6472, "h": 158.27, "l": 148.51, "o": 158.01, "pc": 157.51, "t": 1761150697}, "JD": {"c": 32.37, "d": -0.46, "dp": -1.4012, "h": 32.865, "l": 32.36, "o": 32.71, "pc": 32.83, "t": 1761150703}}