{"SPY": {"c": 668.17, "d": -3.12, "dp": -0.4648, "h": 672.26, "l": 667.6, "o": 672.26, "pc": 671.29, "t": 1761146922}, "SMH": {"c": 337.89, "d": -7.41, "dp": -2.146, "h": 344.86, "l": 337.1, "o": 343.87, "pc": 345.3, "t": 1761146922}, "ABAT": {"c": 5.7755, "d": -0.3245, "dp": -5.3197, "h": 6.39, "l": 5.64, "o": 5.68, "pc": 6.1, "t": 1761146922}, "UUUU": {"c": 20.62, "d": -0.01, "dp": -0.0485, "h": 21.37, "l": 18.76, "o": 18.89, "pc": 20.63, "t": 1761146922}, "ALAB": {"c": 149.395, "d": -8.115, "dp": -5.1521, "h": 158.27, "l": 148.75, "o": 158.01, "pc": 157.51, "t": 1761146922}, "JD": {"c": 32.59, "d": -0.24, "dp": -0.731, "h": 32.865, "l": 32.47, "o": 32.71, "pc": 32.83, "t": 1761146912}}