{"SPY": {"c": 665.3101, "d": -5.9799, "dp": -0.8908, "h": 672.26, "l": 664.01, "o": 672.26, "pc": 671.29, "t": 1761154247}, "SMH": {"c": 334.71, "d": -10.59, "dp": -3.0669, "h": 344.86, "l": 334.17, "o": 343.87, "pc": 345.3, "t": 1761154247}, "ABAT": {"c": 5.58, "d": -0.52, "dp": -8.5246, "h": 6.39, "l": 5.51, "o": 5.68, "pc": 6.1, "t": 1761154229}, "UUUU": {"c": 21.04, "d": 0.41, "dp": 1.9874, "h": 21.5, "l": 18.76, "o": 18.89, "pc": 20.63, "t": 1761154247}, "ALAB": {"c": 150.74, "d": -6.77, "dp": -4.2981, "h": 158.27, "l": 148.51, "o": 158.01, "pc": 157.51, "t": 1761154243}, "JD": {"c": 32.38, "d": -0.45, "dp": -1.3707, "h": 32.865, "l": 32.165, "o": 32.71, "pc": 32.83, "t": 1761154240}}