{"SPY": {"c": 669.91, "d": -1.38, "dp": -0.2056, "h": 672.26, "l": 668.09, "o": 672.26, "pc": 671.29, "t": 1761145141}, "SMH": {"c": 340.38, "d": -4.92, "dp": -1.4248, "h": 344.86, "l": 337.5, "o": 343.87, "pc": 345.3, "t": 1761145140}, "ABAT": {"c": 6.015, "d": -0.085, "dp": -1.3934, "h": 6.39, "l": 5.64, "o": 5.68, "pc": 6.1, "t": 1761145139}, "UUUU": {"c": 21.07, "d": 0.44, "dp": 2.1328, "h": 21.12, "l": 18.76, "o": 18.89, "pc": 20.63, "t": 1761145141}, "ALAB": {"c": 151.975, "d": -5.535, "dp": -3.5141, "h": 158.27, "l": 148.75, "o": 158.01, "pc": 157.51, "t": 1761145140}, "JD": {"c": 32.615, "d": -0.215, "dp": -0.6549, "h": 32.865, "l": 32.47, "o": 32.71, "pc": 32.83, "t": 1761145140}}