{"SPY": {"c": 665.41, "d": -5.88, "dp": -0.8759, "h": 672.26, "l": 664.01, "o": 672.26, "pc": 671.29, "t": 1761154657}, "SMH": {"c": 334.91, "d": -10.39, "dp": -3.009, "h": 344.86, "l": 334.17, "o": 343.87, "pc": 345.3, "t": 1761154642}, "ABAT": {"c": 5.555, "d": -0.545, "dp": -8.9344, "h": 6.39, "l": 5.51, "o": 5.68, "pc": 6.1, "t": 1761154651}, "UUUU": {"c": 21.31, "d": 0.68, "dp": 3.2962, "h": 21.5, "l": 18.76, "o": 18.89, "pc": 20.63, "t": 1761154657}, "ALAB": {"c": 150.32, "d": -7.19, "dp": -4.5648, "h": 158.27, "l": 148.51, "o": 158.01, "pc": 157.51, "t": 1761154647}, "JD": {"c": 32.41, "d": -0.42, "dp": -1.2793, "h": 32.865, "l": 32.165, "o": 32.71, "pc": 32.83, "t": 1761154657}}